bqgcs/__init__.py
bqgcs/__version__.py
bqgcs/bq.py
bqgcs/gcs.py
bqgcs/misc.py
bqgcs/pd.py
bqgcs-0.1.5.dist-info/DESCRIPTION.rst
bqgcs-0.1.5.dist-info/METADATA
bqgcs-0.1.5.dist-info/RECORD
bqgcs-0.1.5.dist-info/WHEEL
bqgcs-0.1.5.dist-info/metadata.json
bqgcs-0.1.5.dist-info/top_level.txt
