Metadata-Version: 2.0
Name: bqgcs
Version: 0.1.5
Summary: Google Cloud Storage Connector for Google BigQuery
Home-page: https://github.com/orisano/bqgcs
Author: Nao YONASHIRO
Author-email: owan.orisano@gmail.com
License: MIT
Platform: UNKNOWN
Classifier: Development Status :: 2 - Pre-Alpha
Classifier: License :: OSI Approved :: MIT License
Classifier: Programming Language :: Python
Classifier: Programming Language :: Python :: 2.7
Classifier: Programming Language :: Python :: 3.6
Classifier: Programming Language :: Python :: Implementation :: CPython
Classifier: Topic :: Software Development :: Libraries
Classifier: Topic :: Software Development :: Libraries :: Python Modules
Classifier: Topic :: Utilities
Requires-Dist: six
Requires-Dist: google-cloud-bigquery
